{"id": 41473, "framework": "flaml", "results": [{"seed": "2", "accuracy_score": 0.23553719008264462, "average_precision_score": -1.0, "balanced_accuracy_score": 0.033596652267911364, "cohen_kappa_score": 0.17508487302442788, "f1_score_macro": 0.0272415379119418, "f1_score_micro": 0.23553719008264462, "f1_score_weighted": 0.16875048949639007, "matthews_corrcoef": 0.19702166736152602, "precision_score": -1.0, "recall_score": -1.0, "roc_auc_score": -1.0, "coverage_error": -1.0, "label_ranking_average_precision_score": -1.0, "label_ranking_loss": -1.0, "training_time": 301.1897732439975, "test_time": 0.08364180999342352}, {"seed": "3", "accuracy_score": 0.2809917355371901, "average_precision_score": -1.0, "balanced_accuracy_score": 0.045747875340338605, "cohen_kappa_score": 0.21763607480282043, "f1_score_macro": 0.040099113089278604, "f1_score_micro": 0.2809917355371901, "f1_score_weighted": 0.20934586450158035, "matthews_corrcoef": 0.2343271382775923, "precision_score": -1.0, "recall_score": -1.0, "roc_auc_score": -1.0, "coverage_error": -1.0, "label_ranking_average_precision_score": -1.0, "label_ranking_loss": -1.0, "training_time": 300.5352609230031, "test_time": 0.11178507300792262}, {"seed": "5", "accuracy_score": 0.17768595041322313, "average_precision_score": -1.0, "balanced_accuracy_score": 0.025639398059418696, "cohen_kappa_score": 0.13249148848017578, "f1_score_macro": 0.01596002041936172, "f1_score_micro": 0.17768595041322313, "f1_score_weighted": 0.14612690698109015, "matthews_corrcoef": 0.1336538372056357, "precision_score": -1.0, "recall_score": -1.0, "roc_auc_score": -1.0, "coverage_error": -1.0, "label_ranking_average_precision_score": -1.0, "label_ranking_loss": -1.0, "training_time": 303.5527298269735, "test_time": 0.038071544986451045}, {"seed": "7", "accuracy_score": 0.14669421487603307, "average_precision_score": -1.0, "balanced_accuracy_score": 0.033388213535656505, "cohen_kappa_score": 0.1072104905849145, "f1_score_macro": 0.02415084676421013, "f1_score_micro": 0.14669421487603307, "f1_score_weighted": 0.12049203224812403, "matthews_corrcoef": 0.10789582463192994, "precision_score": -1.0, "recall_score": -1.0, "roc_auc_score": -1.0, "coverage_error": -1.0, "label_ranking_average_precision_score": -1.0, "label_ranking_loss": -1.0, "training_time": 302.5453674700111, "test_time": 0.041386183991562575}, {"seed": "11", "accuracy_score": 0.2644628099173554, "average_precision_score": -1.0, "balanced_accuracy_score": 0.05667246965736995, "cohen_kappa_score": 0.21088161209068013, "f1_score_macro": 0.045983253064731215, "f1_score_micro": 0.2644628099173554, "f1_score_weighted": 0.19534444461594505, "matthews_corrcoef": 0.2229029142421651, "precision_score": -1.0, "recall_score": -1.0, "roc_auc_score": -1.0, "coverage_error": -1.0, "label_ranking_average_precision_score": -1.0, "label_ranking_loss": -1.0, "training_time": 300.92269125799066, "test_time": 0.11639142798958346}, {"seed": "13", "accuracy_score": 0.2727272727272727, "average_precision_score": -1.0, "balanced_accuracy_score": 0.062158502065042594, "cohen_kappa_score": 0.21218931354188342, "f1_score_macro": 0.05700414126686725, "f1_score_micro": 0.2727272727272727, "f1_score_weighted": 0.20999925392647212, "matthews_corrcoef": 0.22119110862836674, "precision_score": -1.0, "recall_score": -1.0, "roc_auc_score": -1.0, "coverage_error": -1.0, "label_ranking_average_precision_score": -1.0, "label_ranking_loss": -1.0, "training_time": 303.0694722920016, "test_time": 0.0725872979965061}, {"seed": "17", "accuracy_score": 0.04132231404958678, "average_precision_score": -1.0, "balanced_accuracy_score": 0.007832250032690622, "cohen_kappa_score": -0.005327101966998926, "f1_score_macro": 0.004815921787680999, "f1_score_micro": 0.04132231404958678, "f1_score_weighted": 0.03275176555634221, "matthews_corrcoef": -0.0055886211003248745, "precision_score": -1.0, "recall_score": -1.0, "roc_auc_score": -1.0, "coverage_error": -1.0, "label_ranking_average_precision_score": -1.0, "label_ranking_loss": -1.0, "training_time": 312.72942475101445, "test_time": 0.018256194016430527}, {"seed": "19", "accuracy_score": 0.25206611570247933, "average_precision_score": -1.0, "balanced_accuracy_score": 0.056600143603802784, "cohen_kappa_score": 0.18902831328368352, "f1_score_macro": 0.04865967137481328, "f1_score_micro": 0.25206611570247933, "f1_score_weighted": 0.16576029753497556, "matthews_corrcoef": 0.20189936467700717, "precision_score": -1.0, "recall_score": -1.0, "roc_auc_score": -1.0, "coverage_error": -1.0, "label_ranking_average_precision_score": -1.0, "label_ranking_loss": -1.0, "training_time": 301.6227947009902, "test_time": 0.09838255899376236}, {"seed": "23", "accuracy_score": 0.2603305785123967, "average_precision_score": -1.0, "balanced_accuracy_score": 0.06462208443565333, "cohen_kappa_score": 0.19772938785148408, "f1_score_macro": 0.0604521980435411, "f1_score_micro": 0.2603305785123967, "f1_score_weighted": 0.18586219914299432, "matthews_corrcoef": 0.21332299608143748, "precision_score": -1.0, "recall_score": -1.0, "roc_auc_score": -1.0, "coverage_error": -1.0, "label_ranking_average_precision_score": -1.0, "label_ranking_loss": -1.0, "training_time": 300.48785723900073, "test_time": 0.1054760770057328}, {"seed": "29", "accuracy_score": 0.29958677685950413, "average_precision_score": -1.0, "balanced_accuracy_score": 0.05135266718161177, "cohen_kappa_score": 0.23526587836105772, "f1_score_macro": 0.04749906495852743, "f1_score_micro": 0.29958677685950413, "f1_score_weighted": 0.22387457205131603, "matthews_corrcoef": 0.2583358995573604, "precision_score": -1.0, "recall_score": -1.0, "roc_auc_score": -1.0, "coverage_error": -1.0, "label_ranking_average_precision_score": -1.0, "label_ranking_loss": -1.0, "training_time": 302.5192522240104, "test_time": 0.11205162000260316}, {"seed": "31", "accuracy_score": 0.17148760330578514, "average_precision_score": -1.0, "balanced_accuracy_score": 0.04139222924636274, "cohen_kappa_score": 0.12573199517108424, "f1_score_macro": 0.0229890742319165, "f1_score_micro": 0.17148760330578514, "f1_score_weighted": 0.13080783070194363, "matthews_corrcoef": 0.12897474219167057, "precision_score": -1.0, "recall_score": -1.0, "roc_auc_score": -1.0, "coverage_error": -1.0, "label_ranking_average_precision_score": -1.0, "label_ranking_loss": -1.0, "training_time": 300.0643669650017, "test_time": 0.037147608993109316}, {"seed": "37", "accuracy_score": 0.2644628099173554, "average_precision_score": -1.0, "balanced_accuracy_score": 0.0408532352995083, "cohen_kappa_score": 0.2044141752279811, "f1_score_macro": 0.03084492107311819, "f1_score_micro": 0.2644628099173554, "f1_score_weighted": 0.1769591713507067, "matthews_corrcoef": 0.2176090376994706, "precision_score": -1.0, "recall_score": -1.0, "roc_auc_score": -1.0, "coverage_error": -1.0, "label_ranking_average_precision_score": -1.0, "label_ranking_loss": -1.0, "training_time": 300.44108350601164, "test_time": 0.0975310729991179}, {"seed": "41", "accuracy_score": 0.1756198347107438, "average_precision_score": -1.0, "balanced_accuracy_score": 0.06261724310683024, "cohen_kappa_score": 0.13491672415492262, "f1_score_macro": 0.03838766630771059, "f1_score_micro": 0.1756198347107438, "f1_score_weighted": 0.14562878566195187, "matthews_corrcoef": 0.13728533772728735, "precision_score": -1.0, "recall_score": -1.0, "roc_auc_score": -1.0, "coverage_error": -1.0, "label_ranking_average_precision_score": -1.0, "label_ranking_loss": -1.0, "training_time": 309.64826760900905, "test_time": 0.016423560999101028}, {"seed": "43", "accuracy_score": 0.25, "average_precision_score": -1.0, "balanced_accuracy_score": 0.044912207286585216, "cohen_kappa_score": 0.19904446257858333, "f1_score_macro": 0.036414023950543925, "f1_score_micro": 0.25, "f1_score_weighted": 0.18851974457704088, "matthews_corrcoef": 0.21171875760088166, "precision_score": -1.0, "recall_score": -1.0, "roc_auc_score": -1.0, "coverage_error": -1.0, "label_ranking_average_precision_score": -1.0, "label_ranking_loss": -1.0, "training_time": 301.96544402698055, "test_time": 0.0787757959915325}, {"seed": "47", "accuracy_score": 0.21487603305785125, "average_precision_score": -1.0, "balanced_accuracy_score": 0.050467854112355395, "cohen_kappa_score": 0.174702606651021, "f1_score_macro": 0.03318966099438927, "f1_score_micro": 0.21487603305785125, "f1_score_weighted": 0.19336974183030187, "matthews_corrcoef": 0.17684382024402437, "precision_score": -1.0, "recall_score": -1.0, "roc_auc_score": -1.0, "coverage_error": -1.0, "label_ranking_average_precision_score": -1.0, "label_ranking_loss": -1.0, "training_time": 324.2877573839796, "test_time": 0.01872996101155877}, {"seed": "53", "accuracy_score": 0.1756198347107438, "average_precision_score": -1.0, "balanced_accuracy_score": 0.04703040739605051, "cohen_kappa_score": 0.12959056736437868, "f1_score_macro": 0.028942817651810622, "f1_score_micro": 0.1756198347107438, "f1_score_weighted": 0.15251337758257058, "matthews_corrcoef": 0.13058907464058628, "precision_score": -1.0, "recall_score": -1.0, "roc_auc_score": -1.0, "coverage_error": -1.0, "label_ranking_average_precision_score": -1.0, "label_ranking_loss": -1.0, "training_time": 369.0539499990118, "test_time": 0.02882609999505803}, {"seed": "59", "accuracy_score": 0.1797520661157025, "average_precision_score": -1.0, "balanced_accuracy_score": 0.040937497574567494, "cohen_kappa_score": 0.13235407005359912, "f1_score_macro": 0.03242165788925017, "f1_score_micro": 0.17975206611570252, "f1_score_weighted": 0.15658915720347868, "matthews_corrcoef": 0.13443508627431328, "precision_score": -1.0, "recall_score": -1.0, "roc_auc_score": -1.0, "coverage_error": -1.0, "label_ranking_average_precision_score": -1.0, "label_ranking_loss": -1.0, "training_time": 302.5000684809929, "test_time": 0.03561663400614634}, {"seed": "61", "accuracy_score": 0.2603305785123967, "average_precision_score": -1.0, "balanced_accuracy_score": 0.05335774504036862, "cohen_kappa_score": 0.19739493346056047, "f1_score_macro": 0.047103631841484035, "f1_score_micro": 0.2603305785123967, "f1_score_weighted": 0.1893505071983275, "matthews_corrcoef": 0.21425688395928966, "precision_score": -1.0, "recall_score": -1.0, "roc_auc_score": -1.0, "coverage_error": -1.0, "label_ranking_average_precision_score": -1.0, "label_ranking_loss": -1.0, "training_time": 301.77983575398684, "test_time": 0.10270074300933629}, {"seed": "67", "accuracy_score": 0.09917355371900827, "average_precision_score": -1.0, "balanced_accuracy_score": 0.012205506264912205, "cohen_kappa_score": 0.02200924119329095, "f1_score_macro": 0.004228127243497834, "f1_score_micro": 0.09917355371900827, "f1_score_weighted": 0.033713851663165775, "matthews_corrcoef": 0.02946369266423896, "precision_score": -1.0, "recall_score": -1.0, "roc_auc_score": -1.0, "coverage_error": -1.0, "label_ranking_average_precision_score": -1.0, "label_ranking_loss": -1.0, "training_time": 309.80181660401286, "test_time": 0.016988788003800437}, {"seed": "71", "accuracy_score": 0.11570247933884298, "average_precision_score": -1.0, "balanced_accuracy_score": 0.03620390973085985, "cohen_kappa_score": 0.08481555113761863, "f1_score_macro": 0.025920814022932524, "f1_score_micro": 0.11570247933884298, "f1_score_weighted": 0.11725053411667408, "matthews_corrcoef": 0.08491875522616275, "precision_score": -1.0, "recall_score": -1.0, "roc_auc_score": -1.0, "coverage_error": -1.0, "label_ranking_average_precision_score": -1.0, "label_ranking_loss": -1.0, "training_time": 304.8243762310012, "test_time": 0.013608007982838899}]}