{"id": 41470, "framework": "mljar", "results": [{"seed": "2", "accuracy_score": -1.0, "average_precision_score": -1.0, "balanced_accuracy_score": -1.0, "cohen_kappa_score": -1.0, "f1_score_macro": -1.0, "f1_score_micro": -1.0, "f1_score_weighted": -1.0, "matthews_corrcoef": -1.0, "precision_score": -1.0, "recall_score": -1.0, "roc_auc_score": -1.0, "coverage_error": -1.0, "label_ranking_average_precision_score": -1.0, "label_ranking_loss": -1.0, "training_time": 35.30448483600048, "test_time": 0.04789441201137379}, {"seed": "3", "accuracy_score": -1.0, "average_precision_score": -1.0, "balanced_accuracy_score": -1.0, "cohen_kappa_score": -1.0, "f1_score_macro": -1.0, "f1_score_micro": -1.0, "f1_score_weighted": -1.0, "matthews_corrcoef": -1.0, "precision_score": -1.0, "recall_score": -1.0, "roc_auc_score": -1.0, "coverage_error": -1.0, "label_ranking_average_precision_score": -1.0, "label_ranking_loss": -1.0, "training_time": 31.39867170099751, "test_time": 0.23786175399436615}, {"seed": "5", "accuracy_score": -1.0, "average_precision_score": -1.0, "balanced_accuracy_score": -1.0, "cohen_kappa_score": -1.0, "f1_score_macro": -1.0, "f1_score_micro": -1.0, "f1_score_weighted": -1.0, "matthews_corrcoef": -1.0, "precision_score": -1.0, "recall_score": -1.0, "roc_auc_score": -1.0, "coverage_error": -1.0, "label_ranking_average_precision_score": -1.0, "label_ranking_loss": -1.0, "training_time": 35.89223538400256, "test_time": 0.043351758999051526}, {"seed": "7", "accuracy_score": -1.0, "average_precision_score": -1.0, "balanced_accuracy_score": -1.0, "cohen_kappa_score": -1.0, "f1_score_macro": -1.0, "f1_score_micro": -1.0, "f1_score_weighted": -1.0, "matthews_corrcoef": -1.0, "precision_score": -1.0, "recall_score": -1.0, "roc_auc_score": -1.0, "coverage_error": -1.0, "label_ranking_average_precision_score": -1.0, "label_ranking_loss": -1.0, "training_time": 33.79007903201273, "test_time": 0.09424652700545266}, {"seed": "11", "accuracy_score": -1.0, "average_precision_score": -1.0, "balanced_accuracy_score": -1.0, "cohen_kappa_score": -1.0, "f1_score_macro": -1.0, "f1_score_micro": -1.0, "f1_score_weighted": -1.0, "matthews_corrcoef": -1.0, "precision_score": -1.0, "recall_score": -1.0, "roc_auc_score": -1.0, "coverage_error": -1.0, "label_ranking_average_precision_score": -1.0, "label_ranking_loss": -1.0, "training_time": 34.62072856898885, "test_time": 0.09459468501154333}, {"seed": "13", "accuracy_score": -1.0, "average_precision_score": -1.0, "balanced_accuracy_score": -1.0, "cohen_kappa_score": -1.0, "f1_score_macro": -1.0, "f1_score_micro": -1.0, "f1_score_weighted": -1.0, "matthews_corrcoef": -1.0, "precision_score": -1.0, "recall_score": -1.0, "roc_auc_score": -1.0, "coverage_error": -1.0, "label_ranking_average_precision_score": -1.0, "label_ranking_loss": -1.0, "training_time": 33.10934274501051, "test_time": 0.10551698599010706}, {"seed": "17", "accuracy_score": -1.0, "average_precision_score": -1.0, "balanced_accuracy_score": -1.0, "cohen_kappa_score": -1.0, "f1_score_macro": -1.0, "f1_score_micro": -1.0, "f1_score_weighted": -1.0, "matthews_corrcoef": -1.0, "precision_score": -1.0, "recall_score": -1.0, "roc_auc_score": -1.0, "coverage_error": -1.0, "label_ranking_average_precision_score": -1.0, "label_ranking_loss": -1.0, "training_time": 33.37864381200052, "test_time": 0.04645902299671434}, {"seed": "19", "accuracy_score": -1.0, "average_precision_score": -1.0, "balanced_accuracy_score": -1.0, "cohen_kappa_score": -1.0, "f1_score_macro": -1.0, "f1_score_micro": -1.0, "f1_score_weighted": -1.0, "matthews_corrcoef": -1.0, "precision_score": -1.0, "recall_score": -1.0, "roc_auc_score": -1.0, "coverage_error": -1.0, "label_ranking_average_precision_score": -1.0, "label_ranking_loss": -1.0, "training_time": 33.852206716983346, "test_time": 0.09447942601400428}, {"seed": "23", "accuracy_score": -1.0, "average_precision_score": -1.0, "balanced_accuracy_score": -1.0, "cohen_kappa_score": -1.0, "f1_score_macro": -1.0, "f1_score_micro": -1.0, "f1_score_weighted": -1.0, "matthews_corrcoef": -1.0, "precision_score": -1.0, "recall_score": -1.0, "roc_auc_score": -1.0, "coverage_error": -1.0, "label_ranking_average_precision_score": -1.0, "label_ranking_loss": -1.0, "training_time": 34.47799823898822, "test_time": 0.12747765102540143}, {"seed": "29", "accuracy_score": -1.0, "average_precision_score": -1.0, "balanced_accuracy_score": -1.0, "cohen_kappa_score": -1.0, "f1_score_macro": -1.0, "f1_score_micro": -1.0, "f1_score_weighted": -1.0, "matthews_corrcoef": -1.0, "precision_score": -1.0, "recall_score": -1.0, "roc_auc_score": -1.0, "coverage_error": -1.0, "label_ranking_average_precision_score": -1.0, "label_ranking_loss": -1.0, "training_time": 34.82393799300189, "test_time": 0.24297574799857102}, {"seed": "31", "accuracy_score": -1.0, "average_precision_score": -1.0, "balanced_accuracy_score": -1.0, "cohen_kappa_score": -1.0, "f1_score_macro": -1.0, "f1_score_micro": -1.0, "f1_score_weighted": -1.0, "matthews_corrcoef": -1.0, "precision_score": -1.0, "recall_score": -1.0, "roc_auc_score": -1.0, "coverage_error": -1.0, "label_ranking_average_precision_score": -1.0, "label_ranking_loss": -1.0, "training_time": 34.552223685983336, "test_time": 0.10163128099520691}, {"seed": "37", "accuracy_score": -1.0, "average_precision_score": -1.0, "balanced_accuracy_score": -1.0, "cohen_kappa_score": -1.0, "f1_score_macro": -1.0, "f1_score_micro": -1.0, "f1_score_weighted": -1.0, "matthews_corrcoef": -1.0, "precision_score": -1.0, "recall_score": -1.0, "roc_auc_score": -1.0, "coverage_error": -1.0, "label_ranking_average_precision_score": -1.0, "label_ranking_loss": -1.0, "training_time": 33.21654299501097, "test_time": 0.10356477001914755}, {"seed": "41", "accuracy_score": -1.0, "average_precision_score": -1.0, "balanced_accuracy_score": -1.0, "cohen_kappa_score": -1.0, "f1_score_macro": -1.0, "f1_score_micro": -1.0, "f1_score_weighted": -1.0, "matthews_corrcoef": -1.0, "precision_score": -1.0, "recall_score": -1.0, "roc_auc_score": -1.0, "coverage_error": -1.0, "label_ranking_average_precision_score": -1.0, "label_ranking_loss": -1.0, "training_time": 34.57935897199786, "test_time": 0.1770811630121898}, {"seed": "43", "accuracy_score": -1.0, "average_precision_score": -1.0, "balanced_accuracy_score": -1.0, "cohen_kappa_score": -1.0, "f1_score_macro": -1.0, "f1_score_micro": -1.0, "f1_score_weighted": -1.0, "matthews_corrcoef": -1.0, "precision_score": -1.0, "recall_score": -1.0, "roc_auc_score": -1.0, "coverage_error": -1.0, "label_ranking_average_precision_score": -1.0, "label_ranking_loss": -1.0, "training_time": 29.8997759349877, "test_time": 0.28298887101118453}, {"seed": "47", "accuracy_score": -1.0, "average_precision_score": -1.0, "balanced_accuracy_score": -1.0, "cohen_kappa_score": -1.0, "f1_score_macro": -1.0, "f1_score_micro": -1.0, "f1_score_weighted": -1.0, "matthews_corrcoef": -1.0, "precision_score": -1.0, "recall_score": -1.0, "roc_auc_score": -1.0, "coverage_error": -1.0, "label_ranking_average_precision_score": -1.0, "label_ranking_loss": -1.0, "training_time": 35.42726294900058, "test_time": 0.15791258600074798}, {"seed": "53", "accuracy_score": -1.0, "average_precision_score": -1.0, "balanced_accuracy_score": -1.0, "cohen_kappa_score": -1.0, "f1_score_macro": -1.0, "f1_score_micro": -1.0, "f1_score_weighted": -1.0, "matthews_corrcoef": -1.0, "precision_score": -1.0, "recall_score": -1.0, "roc_auc_score": -1.0, "coverage_error": -1.0, "label_ranking_average_precision_score": -1.0, "label_ranking_loss": -1.0, "training_time": 33.07744596598786, "test_time": 0.24582593599916436}, {"seed": "59", "accuracy_score": -1.0, "average_precision_score": -1.0, "balanced_accuracy_score": -1.0, "cohen_kappa_score": -1.0, "f1_score_macro": -1.0, "f1_score_micro": -1.0, "f1_score_weighted": -1.0, "matthews_corrcoef": -1.0, "precision_score": -1.0, "recall_score": -1.0, "roc_auc_score": -1.0, "coverage_error": -1.0, "label_ranking_average_precision_score": -1.0, "label_ranking_loss": -1.0, "training_time": 36.511782440007664, "test_time": 0.21995115402387455}, {"seed": "61", "accuracy_score": -1.0, "average_precision_score": -1.0, "balanced_accuracy_score": -1.0, "cohen_kappa_score": -1.0, "f1_score_macro": -1.0, "f1_score_micro": -1.0, "f1_score_weighted": -1.0, "matthews_corrcoef": -1.0, "precision_score": -1.0, "recall_score": -1.0, "roc_auc_score": -1.0, "coverage_error": -1.0, "label_ranking_average_precision_score": -1.0, "label_ranking_loss": -1.0, "training_time": 33.86578011501115, "test_time": 0.3142288050148636}, {"seed": "67", "accuracy_score": -1.0, "average_precision_score": -1.0, "balanced_accuracy_score": -1.0, "cohen_kappa_score": -1.0, "f1_score_macro": -1.0, "f1_score_micro": -1.0, "f1_score_weighted": -1.0, "matthews_corrcoef": -1.0, "precision_score": -1.0, "recall_score": -1.0, "roc_auc_score": -1.0, "coverage_error": -1.0, "label_ranking_average_precision_score": -1.0, "label_ranking_loss": -1.0, "training_time": 33.84613350199652, "test_time": 0.28407253097975627}, {"seed": "71", "accuracy_score": -1.0, "average_precision_score": -1.0, "balanced_accuracy_score": -1.0, "cohen_kappa_score": -1.0, "f1_score_macro": -1.0, "f1_score_micro": -1.0, "f1_score_weighted": -1.0, "matthews_corrcoef": -1.0, "precision_score": -1.0, "recall_score": -1.0, "roc_auc_score": -1.0, "coverage_error": -1.0, "label_ranking_average_precision_score": -1.0, "label_ranking_loss": -1.0, "training_time": 32.820374915987486, "test_time": 0.267442107986426}]}