{
    "id": 40945,
    "framework": "autokeras",
    "results": [
        {
            "seed": "2",
            "accuracy_score": 0.9465648854961832,
            "average_precision_score": 0.958708936395372,
            "balanced_accuracy_score": 0.9484400656814449,
            "cohen_kappa_score": 0.8815933888566079,
            "f1_score_macro": 0.9407622739018087,
            "f1_score_micro": 0.9465648854961832,
            "f1_score_weighted": 0.9469894668323569,
            "matthews_corrcoef": 0.8827306924861993,
            "precision_score": 0.9763313609467456,
            "recall_score": 0.9428571428571428,
            "roc_auc_score": 0.948440065681445,
            "coverage_error": -1.0,
            "label_ranking_average_precision_score": -1.0,
            "label_ranking_loss": -1.0,
            "training_time": 33.60920078100753,
            "test_time": 0.6832964459899813
        },
        {
            "seed": "3",
            "accuracy_score": 0.9465648854961832,
            "average_precision_score": 0.9311890516470669,
            "balanced_accuracy_score": 0.9446420104314841,
            "cohen_kappa_score": 0.89107970067704,
            "f1_score_macro": 0.9455366157866603,
            "f1_score_micro": 0.9465648854961832,
            "f1_score_weighted": 0.9465077594012098,
            "matthews_corrcoef": 0.8911875921190237,
            "precision_score": 0.9466666666666667,
            "recall_score": 0.9594594594594594,
            "roc_auc_score": 0.9446420104314841,
            "coverage_error": -1.0,
            "label_ranking_average_precision_score": -1.0,
            "label_ranking_loss": -1.0,
            "training_time": 31.23512616699736,
            "test_time": 0.6949217299988959
        },
        {
            "seed": "5",
            "accuracy_score": 0.9351145038167938,
            "average_precision_score": 0.9286635642026766,
            "balanced_accuracy_score": 0.9303086419753086,
            "cohen_kappa_score": 0.8622673016265694,
            "f1_score_macro": 0.9311325860069579,
            "f1_score_micro": 0.9351145038167938,
            "f1_score_weighted": 0.9350512987721934,
            "matthews_corrcoef": 0.8622956031342732,
            "precision_score": 0.9447852760736196,
            "recall_score": 0.9506172839506173,
            "roc_auc_score": 0.9303086419753087,
            "coverage_error": -1.0,
            "label_ranking_average_precision_score": -1.0,
            "label_ranking_loss": -1.0,
            "training_time": 38.2675074620056,
            "test_time": 0.7642922739905771
        },
        {
            "seed": "7",
            "accuracy_score": 0.9351145038167938,
            "average_precision_score": 0.9132001561587968,
            "balanced_accuracy_score": 0.9290071770334928,
            "cohen_kappa_score": 0.8656248114402945,
            "f1_score_macro": 0.9327627070030041,
            "f1_score_micro": 0.9351145038167938,
            "f1_score_weighted": 0.9347785328433954,
            "matthews_corrcoef": 0.8669529234761146,
            "precision_score": 0.9245283018867925,
            "recall_score": 0.9671052631578947,
            "roc_auc_score": 0.9290071770334928,
            "coverage_error": -1.0,
            "label_ranking_average_precision_score": -1.0,
            "label_ranking_loss": -1.0,
            "training_time": 29.446075935993576,
            "test_time": 0.6445555449899985
        },
        {
            "seed": "11",
            "accuracy_score": 0.9580152671755725,
            "average_precision_score": 0.9371889772653131,
            "balanced_accuracy_score": 0.9496250604741171,
            "cohen_kappa_score": 0.9116547115443566,
            "f1_score_macro": 0.9557724475545939,
            "f1_score_micro": 0.9580152671755725,
            "f1_score_weighted": 0.9576731421486435,
            "matthews_corrcoef": 0.9140456738120082,
            "precision_score": 0.9393939393939394,
            "recall_score": 0.9935897435897436,
            "roc_auc_score": 0.9496250604741171,
            "coverage_error": -1.0,
            "label_ranking_average_precision_score": -1.0,
            "label_ranking_loss": -1.0,
            "training_time": 31.341082301005372,
            "test_time": 0.6391238639916992
        },
        {
            "seed": "13",
            "accuracy_score": 0.9541984732824428,
            "average_precision_score": 0.9468542193903703,
            "balanced_accuracy_score": 0.9495679012345679,
            "cohen_kappa_score": 0.9025901598711117,
            "f1_score_macro": 0.9512920617215095,
            "f1_score_micro": 0.9541984732824428,
            "f1_score_weighted": 0.9541076479211636,
            "matthews_corrcoef": 0.9027091332021572,
            "precision_score": 0.9573170731707317,
            "recall_score": 0.9691358024691358,
            "roc_auc_score": 0.9495679012345677,
            "coverage_error": -1.0,
            "label_ranking_average_precision_score": -1.0,
            "label_ranking_loss": -1.0,
            "training_time": 31.857039402006194,
            "test_time": 0.6423318180022761
        },
        {
            "seed": "17",
            "accuracy_score": 0.9541984732824428,
            "average_precision_score": 0.9469798476459795,
            "balanced_accuracy_score": 0.9526077781127524,
            "cohen_kappa_score": 0.905215556225505,
            "f1_score_macro": 0.9526077781127524,
            "f1_score_micro": 0.9541984732824428,
            "f1_score_weighted": 0.9541984732824428,
            "matthews_corrcoef": 0.905215556225505,
            "precision_score": 0.9612903225806452,
            "recall_score": 0.9612903225806452,
            "roc_auc_score": 0.9526077781127525,
            "coverage_error": -1.0,
            "label_ranking_average_precision_score": -1.0,
            "label_ranking_loss": -1.0,
            "training_time": 31.919186323997565,
            "test_time": 0.5173575270018773
        },
        {
            "seed": "19",
            "accuracy_score": 0.9580152671755725,
            "average_precision_score": 0.9479737990365666,
            "balanced_accuracy_score": 0.9414091060152875,
            "cohen_kappa_score": 0.9021259254228079,
            "f1_score_macro": 0.9510222116479445,
            "f1_score_micro": 0.9580152671755725,
            "f1_score_weighted": 0.9575208087039221,
            "matthews_corrcoef": 0.9038808118502586,
            "precision_score": 0.9510869565217391,
            "recall_score": 0.9887005649717514,
            "roc_auc_score": 0.9414091060152875,
            "coverage_error": -1.0,
            "label_ranking_average_precision_score": -1.0,
            "label_ranking_loss": -1.0,
            "training_time": 32.20067407800525,
            "test_time": 0.6819679679902038
        },
        {
            "seed": "23",
            "accuracy_score": 0.9694656488549618,
            "average_precision_score": 0.9565158173802608,
            "balanced_accuracy_score": 0.961578979983888,
            "cohen_kappa_score": 0.9342740671056757,
            "f1_score_macro": 0.9671184738955823,
            "f1_score_micro": 0.9694656488549618,
            "f1_score_weighted": 0.9692644624298721,
            "matthews_corrcoef": 0.9354112562607824,
            "precision_score": 0.9585798816568047,
            "recall_score": 0.9938650306748467,
            "roc_auc_score": 0.961578979983888,
            "coverage_error": -1.0,
            "label_ranking_average_precision_score": -1.0,
            "label_ranking_loss": -1.0,
            "training_time": 52.77600790500583,
            "test_time": 0.7550568029982969
        },
        {
            "seed": "29",
            "accuracy_score": 0.9389312977099237,
            "average_precision_score": 0.9445410707194232,
            "balanced_accuracy_score": 0.934055829228243,
            "cohen_kappa_score": 0.8631228368053288,
            "f1_score_macro": 0.9315569487983282,
            "f1_score_micro": 0.9389312977099237,
            "f1_score_weighted": 0.9391027941962399,
            "matthews_corrcoef": 0.8632491998244518,
            "precision_score": 0.9595375722543352,
            "recall_score": 0.9485714285714286,
            "roc_auc_score": 0.934055829228243,
            "coverage_error": -1.0,
            "label_ranking_average_precision_score": -1.0,
            "label_ranking_loss": -1.0,
            "training_time": 58.681690637997235,
            "test_time": 0.5710743490053574
        },
        {
            "seed": "31",
            "accuracy_score": 0.9465648854961832,
            "average_precision_score": 0.9445243052113281,
            "balanced_accuracy_score": 0.9476310726310726,
            "cohen_kappa_score": 0.890337239894762,
            "f1_score_macro": 0.9451555023923445,
            "f1_score_micro": 0.9465648854961832,
            "f1_score_weighted": 0.9466991124584536,
            "matthews_corrcoef": 0.8907745874529563,
            "precision_score": 0.9666666666666667,
            "recall_score": 0.9415584415584416,
            "roc_auc_score": 0.9476310726310726,
            "coverage_error": -1.0,
            "label_ranking_average_precision_score": -1.0,
            "label_ranking_loss": -1.0,
            "training_time": 35.33095571999729,
            "test_time": 0.5385173700051382
        },
        {
            "seed": "37",
            "accuracy_score": 0.9541984732824428,
            "average_precision_score": 0.9592658452121188,
            "balanced_accuracy_score": 0.9549952726126694,
            "cohen_kappa_score": 0.9018052345555625,
            "f1_score_macro": 0.9508903467666354,
            "f1_score_micro": 0.9541984732824428,
            "f1_score_weighted": 0.9543930689598431,
            "matthews_corrcoef": 0.9022887006871093,
            "precision_score": 0.9754601226993865,
            "recall_score": 0.9520958083832335,
            "roc_auc_score": 0.9549952726126694,
            "coverage_error": -1.0,
            "label_ranking_average_precision_score": -1.0,
            "label_ranking_loss": -1.0,
            "training_time": 53.53703086699534,
            "test_time": 0.746219011998619
        },
        {
            "seed": "41",
            "accuracy_score": 0.9389312977099237,
            "average_precision_score": 0.9388786531077301,
            "balanced_accuracy_score": 0.9272848122299768,
            "cohen_kappa_score": 0.8598274593727011,
            "f1_score_macro": 0.9299090422685928,
            "f1_score_micro": 0.9389312977099237,
            "f1_score_weighted": 0.9387393348281933,
            "matthews_corrcoef": 0.8599594755773657,
            "precision_score": 0.9497206703910615,
            "recall_score": 0.96045197740113,
            "roc_auc_score": 0.9272848122299767,
            "coverage_error": -1.0,
            "label_ranking_average_precision_score": -1.0,
            "label_ranking_loss": -1.0,
            "training_time": 38.50506339099957,
            "test_time": 0.5250097719981568
        },
        {
            "seed": "43",
            "accuracy_score": 0.950381679389313,
            "average_precision_score": 0.9531450392964167,
            "balanced_accuracy_score": 0.9498619477911646,
            "cohen_kappa_score": 0.8938345489682689,
            "f1_score_macro": 0.9469098277608916,
            "f1_score_micro": 0.950381679389313,
            "f1_score_weighted": 0.9505371354323766,
            "matthews_corrcoef": 0.8941029257421238,
            "precision_score": 0.9693251533742331,
            "recall_score": 0.9518072289156626,
            "roc_auc_score": 0.9498619477911645,
            "coverage_error": -1.0,
            "label_ranking_average_precision_score": -1.0,
            "label_ranking_loss": -1.0,
            "training_time": 31.42610150600376,
            "test_time": 0.6810350170126185
        },
        {
            "seed": "47",
            "accuracy_score": 0.9351145038167938,
            "average_precision_score": 0.9267102547836741,
            "balanced_accuracy_score": 0.9276381284221005,
            "cohen_kappa_score": 0.8605772240656107,
            "f1_score_macro": 0.9302787909146408,
            "f1_score_micro": 0.9351145038167938,
            "f1_score_weighted": 0.9349042554297439,
            "matthews_corrcoef": 0.86083782093976,
            "precision_score": 0.9401197604790419,
            "recall_score": 0.9573170731707317,
            "roc_auc_score": 0.9276381284221005,
            "coverage_error": -1.0,
            "label_ranking_average_precision_score": -1.0,
            "label_ranking_loss": -1.0,
            "training_time": 45.50541870300367,
            "test_time": 0.6461236059985822
        },
        {
            "seed": "53",
            "accuracy_score": 0.9351145038167938,
            "average_precision_score": 0.9032635010321446,
            "balanced_accuracy_score": 0.9226791726791728,
            "cohen_kappa_score": 0.8632651808190581,
            "f1_score_macro": 0.9313956533123855,
            "f1_score_micro": 0.9351145038167938,
            "f1_score_weighted": 0.9342000323812836,
            "matthews_corrcoef": 0.8696174702070448,
            "precision_score": 0.9053254437869822,
            "recall_score": 0.9935064935064936,
            "roc_auc_score": 0.9226791726791728,
            "coverage_error": -1.0,
            "label_ranking_average_precision_score": -1.0,
            "label_ranking_loss": -1.0,
            "training_time": 43.909588800001075,
            "test_time": 0.67307414500101
        },
        {
            "seed": "59",
            "accuracy_score": 0.9312977099236641,
            "average_precision_score": 0.9116034143337288,
            "balanced_accuracy_score": 0.9216772151898734,
            "cohen_kappa_score": 0.854588061174149,
            "f1_score_macro": 0.9272222222222222,
            "f1_score_micro": 0.931297709923664,
            "f1_score_weighted": 0.9307718405428329,
            "matthews_corrcoef": 0.8563783577245364,
            "precision_score": 0.9216867469879518,
            "recall_score": 0.9683544303797469,
            "roc_auc_score": 0.9216772151898734,
            "coverage_error": -1.0,
            "label_ranking_average_precision_score": -1.0,
            "label_ranking_loss": -1.0,
            "training_time": 27.588591132007423,
            "test_time": 0.6561416240001563
        },
        {
            "seed": "61",
            "accuracy_score": 0.9007633587786259,
            "average_precision_score": 0.9168843048052747,
            "balanced_accuracy_score": 0.9063417681974384,
            "cohen_kappa_score": 0.7924815694876013,
            "f1_score_macro": 0.896012700738841,
            "f1_score_micro": 0.9007633587786259,
            "f1_score_weighted": 0.9017813569300085,
            "matthews_corrcoef": 0.7961416354776142,
            "precision_score": 0.954248366013072,
            "recall_score": 0.8848484848484849,
            "roc_auc_score": 0.9063417681974383,
            "coverage_error": -1.0,
            "label_ranking_average_precision_score": -1.0,
            "label_ranking_loss": -1.0,
            "training_time": 44.862315305988886,
            "test_time": 0.6895900279923808
        },
        {
            "seed": "67",
            "accuracy_score": 0.9427480916030534,
            "average_precision_score": 0.9354520293015979,
            "balanced_accuracy_score": 0.9389093137254902,
            "cohen_kappa_score": 0.8793812534528267,
            "f1_score_macro": 0.9396897012108099,
            "f1_score_micro": 0.9427480916030534,
            "f1_score_weighted": 0.9426962544777612,
            "matthews_corrcoef": 0.8794096859741629,
            "precision_score": 0.9503105590062112,
            "recall_score": 0.95625,
            "roc_auc_score": 0.9389093137254902,
            "coverage_error": -1.0,
            "label_ranking_average_precision_score": -1.0,
            "label_ranking_loss": -1.0,
            "training_time": 24.768263766003656,
            "test_time": 0.6550132609991124
        },
        {
            "seed": "71",
            "accuracy_score": 0.9694656488549618,
            "average_precision_score": 0.966194994715299,
            "balanced_accuracy_score": 0.967775659553533,
            "cohen_kappa_score": 0.935551319107066,
            "f1_score_macro": 0.967775659553533,
            "f1_score_micro": 0.9694656488549618,
            "f1_score_weighted": 0.9694656488549618,
            "matthews_corrcoef": 0.935551319107066,
            "precision_score": 0.9751552795031055,
            "recall_score": 0.9751552795031055,
            "roc_auc_score": 0.967775659553533,
            "coverage_error": -1.0,
            "label_ranking_average_precision_score": -1.0,
            "label_ranking_loss": -1.0,
            "training_time": 25.756269873993006,
            "test_time": 0.6535587130056228
        }
    ]
}